aws_ssh_config/__init__.py
aws_ssh_config-0.1.4.data/scripts/aws_ssh_config
aws_ssh_config-0.1.4.dist-info/LICENSE
aws_ssh_config-0.1.4.dist-info/METADATA
aws_ssh_config-0.1.4.dist-info/WHEEL
aws_ssh_config-0.1.4.dist-info/top_level.txt
aws_ssh_config-0.1.4.dist-info/RECORD
