Metadata-Version: 2.1
Name: aws-ssh-config
Version: 0.1.4
Summary: aws_ssh_config generates ssh config file content from given AWS account
Home-page: https://github.com/DmitriyLyalyuev/aws_ssh_config
Author: Dmitriy Lyalyuev
Author-email: dmitriy@lyalyuev.info
License: MIT
Keywords: ssh aws devops sysadmin-tool script
Platform: UNKNOWN
Classifier: Environment :: MacOS X
Classifier: Environment :: Console
Classifier: Intended Audience :: Developers
Classifier: Intended Audience :: System Administrators
Classifier: License :: OSI Approved :: MIT License
Classifier: Natural Language :: English
Classifier: Programming Language :: Python :: 2
Classifier: Programming Language :: Python :: 2.7
Classifier: Programming Language :: Python :: 3
Classifier: Programming Language :: Python :: 3.5
Classifier: Programming Language :: Python :: 3.6
Classifier: Programming Language :: Python :: 3.7
Classifier: Topic :: System :: Systems Administration
Classifier: Topic :: Utilities
Requires-Dist: boto3
